obsidian_parser/__init__.py
obsidian_parser/dataview/evaluator.py
obsidian_parser/errors.py
obsidian_parser/models/dataview.py
obsidian_parser/note.py
obsidian_parser/parser/core.py
obsidian_parser/parser/dataview.py
obsidian_parser/parser/elements.py
obsidian_parser/relationships.py
obsidian_parser/renderer.py
obsidian_parser/vault.py
obsidian_parser/visualisation.py
obsidianmd_parser-0.3.1.dist-info/LICENSE
obsidianmd_parser-0.3.1.dist-info/METADATA
obsidianmd_parser-0.3.1.dist-info/WHEEL
obsidianmd_parser-0.3.1.dist-info/RECORD
