Metadata-Version: 2.3
Name: obsidianmd-parser
Version: 0.3.1
Summary: A Python library for parsing Obsidian Markdown (.md) files and vaults.
License: MIT
Keywords: obsidian,markdown,parser,dataview
Author: paddyd
Author-email: patduf1@gmail.com
Requires-Python: >=3.12,<4.0
Classifier: License :: OSI Approved :: MIT License
Classifier: Programming Language :: Python :: 3
Classifier: Programming Language :: Python :: 3.12
Classifier: Programming Language :: Python :: 3.13
Requires-Dist: pandas (>=2.2.3,<3.0.0)
Requires-Dist: python-frontmatter (>=1.1.0,<2.0.0)
Requires-Dist: pyyaml (>=6.0.2,<7.0.0)
Requires-Dist: typing-extensions (>=4.13.2,<5.0.0)
Project-URL: Documentation, https://codeberg.org/paddyd/obsidianmd-parser
Project-URL: Homepage, https://codeberg.org/paddyd/obsidianmd-parser
Project-URL: Repository, https://codeberg.org/paddyd/obsidianmd-parser
